examples/__init__.py
examples/filter_out_lowest_duplicates.py
examples/sum_all_after.py
examples/provider/__init__.py
examples/provider/dict_t_v_o_values.py
examples/provider/dict_t_v_o_values_sorted.py
script_benchmark_tools/__init__.py
script_benchmark_tools/benchmark.py
script_benchmark_tools/benchmark_report.py
script_benchmark_tools/benchmark_results.py
script_benchmark_tools/execute_benchmarks.py
script_benchmark_tools/result.py
script_benchmark_tools/script.py
script_benchmark_tools/timer.py
script_benchmark_tools/charts/__init__.py
script_benchmark_tools/charts/chart.py
script_benchmark_tools/charts/plot.py
script_benchmark_tools/charts/plot_visual.py
script_benchmark_tools/kwargs_provider/__init__.py
script_benchmark_tools/kwargs_provider/kwargs_provider.py
script_benchmark_tools/kwargs_provider/list_provider.py
script_benchmark_tools/kwargs_provider/np_arange_provider.py
script_benchmark_tools/kwargs_provider/np_array_provider.py
script_benchmark_tools/kwargs_provider/range_provider.py
script_benchmark_tools/run_scripts/__init__.py
script_benchmark_tools/run_scripts/run_scripts_with_n_sized_list.py
script_benchmark_tools/run_scripts/run_scripts_with_n_sized_np_arange.py
script_benchmark_tools/run_scripts/run_scripts_with_n_sized_np_array.py
script_benchmark_tools/run_scripts/run_scripts_with_n_sized_range.py
script_benchmark_tools-0.6.8.dist-info/LICENSE.txt
script_benchmark_tools-0.6.8.dist-info/METADATA
script_benchmark_tools-0.6.8.dist-info/WHEEL
script_benchmark_tools-0.6.8.dist-info/top_level.txt
script_benchmark_tools-0.6.8.dist-info/RECORD
